auction_crawler/__init__.py
auction_crawler/csv_write.py
auction_crawler/main.py
auction_crawler/selenium_crawl.py
auction_crawler-0.1.1.dist-info/METADATA
auction_crawler-0.1.1.dist-info/WHEEL
auction_crawler-0.1.1.dist-info/RECORD
