Metadata-Version: 2.1
Name: auction-crawler
Version: 0.1.1
Summary: 
Author: Vytenis Dambrauskas
Author-email: vytenisdambrauskas@gmail.com
Requires-Python: >=3.12,<4.0
Classifier: Programming Language :: Python :: 3
Classifier: Programming Language :: Python :: 3.12
Requires-Dist: coverage (>=7.4.0,<8.0.0)
Requires-Dist: pytest (>=7.4.4,<8.0.0)
Requires-Dist: requests (>=2.31.0,<3.0.0)
Requires-Dist: selenium (>=4.16.0,<5.0.0)
